
%main <goto-if-2.lua:0,0> (38 instructions, 152 bytes at goto-if-2.lua:0)
0 param, 3 slots, 1 upvalues, 1 locals, 9 constants, 0 functions
	1	[1]	VARARG   	0 2
	2	[2]	EQ       	1 0 -1	; - 1
	3	[2]	JMP      	0 32	; to 36
	4	[3]	JMP      	0 4	; to 9
	5	[4]	GETTABUP 	1 0 -2	; _ENV "error"
	6	[4]	LOADK    	2 -3	; "should never be here!"
	7	[4]	CALL     	1 2 1
	8	[4]	JMP      	0 22	; to 31
	9	[5]	EQ       	1 0 -4	; - 2
	10	[5]	JMP      	0 21	; to 32
	11	[6]	EQ       	1 0 -5	; - 3
	12	[6]	JMP      	0 21	; to 34
	13	[7]	EQ       	1 0 -6	; - 4
	14	[7]	JMP      	0 4	; to 19
	15	[8]	JMP      	0 6	; to 22
	16	[9]	GETTABUP 	1 0 -2	; _ENV "error"
	17	[9]	LOADK    	2 -3	; "should never be here!"
	18	[9]	CALL     	1 2 1
	19	[10]	ADD      	0 0 -1	; - 1
	20	[10]	JMP      	0 10	; to 31
	21	[11]	JMP      	0 0	; to 22
	22	[13]	MUL      	0 0 -4	; - 2
	23	[13]	JMP      	0 7	; to 31
	24	[14]	GETTABUP 	1 0 -2	; _ENV "error"
	25	[14]	LOADK    	2 -3	; "should never be here!"
	26	[14]	CALL     	1 2 1
	27	[15]	JMP      	0 -6	; to 22
	28	[16]	GETTABUP 	1 0 -2	; _ENV "error"
	29	[16]	LOADK    	2 -3	; "should never be here!"
	30	[16]	CALL     	1 2 1
	31	[19]	RETURN   	0 2
	32	[20]	LOADK    	1 -7	; "2"
	33	[20]	RETURN   	1 2
	34	[21]	LOADK    	1 -8	; "3"
	35	[21]	RETURN   	1 2
	36	[22]	LOADK    	1 -9	; "1"
	37	[22]	RETURN   	1 2
	38	[22]	RETURN   	0 1
constants (9) for goto-if-2.lua:0:
	1	1
	2	"error"
	3	"should never be here!"
	4	2
	5	3
	6	4
	7	"2"
	8	"3"
	9	"1"
locals (1) for goto-if-2.lua:0:
	0	a	2	39
upvalues (1) for goto-if-2.lua:0:
	0	_ENV	1	0
